aioasterisk/__init__.py
aioasterisk/ai.py
aioasterisk/wikidata.py
aioasterisk-1.0.0.dist-info/LICENSE
aioasterisk-1.0.0.dist-info/METADATA
aioasterisk-1.0.0.dist-info/WHEEL
aioasterisk-1.0.0.dist-info/top_level.txt
aioasterisk-1.0.0.dist-info/RECORD
