Metadata-Version: 2.1
Name: aioasterisk
Version: 1.0.0
Summary: Async Python library for interacting with the Asterisk FreePBX
Home-page: https://www.asterisk.org/
Download-URL: https://github.com/developerreva/aioasterisk
Author: Developereva
Author-email: developereva@protonmail.com
License: BSD License
Project-URL: Source Code, https://github.com/developerreva/aioasterisk
Project-URL: Documentation, https://github.com/developerreva/aioasterisk#-getting-started
Keywords: python python3 api-client aiohttp api-wrapper asterisk asterisk-api asterisk-async
Classifier: Programming Language :: Python :: 3.6
Classifier: License :: OSI Approved :: MIT License
Classifier: Operating System :: OS Independent
License-File: LICENSE
